{"cameraMode":{"drawMode":0,"name":"Shaded","section":"Shading Mode"},"sceneLighting":true,"audioPlay":false,"sceneViewState":{"m_AlwaysRefresh":false,"showFog":true,"showSkybox":false,"showFlares":true,"showImageEffects":true,"showParticleSystems":true,"showVisualEffectGraphs":true,"m_FxEnabled":true},"in2DMode":false,"pivot":{"x":68.10968017578125,"y":-302.93023681640627,"z":-195.10116577148438},"rotation":{"x":-0.5234600305557251,"y":-0.4255240857601166,"z":0.33971208333969118,"w":-0.6555266380310059},"size":285.0578918457031,"orthographic":false}